tmdb_movies_fetcher_pkg/__init__.py
tmdb_movies_fetcher_pkg/tmdb_movies_fetcher.py
oeademola_movies_fetcher-0.0.1.dist-info/LICENSE
oeademola_movies_fetcher-0.0.1.dist-info/METADATA
oeademola_movies_fetcher-0.0.1.dist-info/WHEEL
oeademola_movies_fetcher-0.0.1.dist-info/top_level.txt
oeademola_movies_fetcher-0.0.1.dist-info/RECORD
