Metadata-Version: 2.1
Name: oeademola-movies-fetcher
Version: 0.0.1
Summary: A library to fetch movies easily from TMDB API
Home-page: https://github.com/pypa/sampleproject
Author: Oluwaseyi Ademola
Author-email: lagpoint@proton.me
Classifier: Programming Language :: Python :: 3
Classifier: License :: OSI Approved :: MIT License
Classifier: Operating System :: OS Independent
Requires-Python: >=3.6
License-File: LICENSE
Requires-Dist: requests
